dragon/__init__.py
dragon/_config.py
dragon/_helpers.py
dragon/base.py
dragon/move_data.py
dragon/sample_test.py
dragon/data/dragon.txt
dragon/data/test_array_delivery_metadata.txt
dragon/data/test_arrays_delivery_metadata.txt
dragon/data/test_arrays_reanalysis_metadata.txt
dragon/data/test_cancer_delivery_metadata.txt
dragon/data/test_cloud_callset_metadata.txt
dragon/data/test_cram_v2_clinical_delivery_metadata.txt
dragon/data/test_cram_v2_delivery_metadata.txt
dragon/data/test_multisample_arrays_metadata.txt
dragon/data/test_on_prem_external_metadata.txt
dragon/data/test_repatienting_metadata.txt
dragon/tests/__init__.py
dragon/tests/test_base.py
dragon/tests/test_helpers.py
dragons_fire-0.2.0.dist-info/LICENSE
dragons_fire-0.2.0.dist-info/METADATA
dragons_fire-0.2.0.dist-info/WHEEL
dragons_fire-0.2.0.dist-info/entry_points.txt
dragons_fire-0.2.0.dist-info/top_level.txt
dragons_fire-0.2.0.dist-info/RECORD
