Metadata-Version: 2.1
Name: dragons-fire
Version: 0.2.0
Summary: A test suite to provide simple testing of workflows
Home-page: https://github.com/broadinstitute/gragons
Author: John Kitonyo
Author-email: jkitonyo@broadinstitute.org
License: UNKNOWN
Keywords: dragon,tests,tickets
Platform: UNKNOWN
Classifier: Development Status :: 3 - Alpha
Classifier: Intended Audience :: Developers
Classifier: Topic :: Software Development :: Build Tools
Classifier: License :: OSI Approved :: MIT License
Classifier: Programming Language :: Python :: 3
Classifier: Programming Language :: Python :: 3.6
Classifier: Programming Language :: Python :: 3.7
Classifier: Programming Language :: Python :: 3.8
Classifier: Programming Language :: Python :: 3.9
Classifier: Programming Language :: Python :: 3 :: Only
Requires-Python: >=3.6, <4
License-File: LICENSE
Requires-Dist: selenium (==3.141.0)
Requires-Dist: chromedriver-autoinstaller
